orderstats/.DS_Store
orderstats/__init__.py
orderstats/classification_utils.py
orderstats/density_estimation.py
orderstats/distributions.py
orderstats/efron_stein.py
orderstats/exponential.py
orderstats/plot_utils.py
orderstats/scoring.py
orderstats/tail_estimation.py
orderstats/utils.py
orderstats/orderstats.egg-info/PKG-INFO
orderstats/orderstats.egg-info/SOURCES.txt
orderstats/orderstats.egg-info/dependency_links.txt
orderstats/orderstats.egg-info/requires.txt
orderstats/orderstats.egg-info/top_level.txt
orderstats-0.1.3.dist-info/LICENSE
orderstats-0.1.3.dist-info/WHEEL
orderstats-0.1.3.dist-info/METADATA
orderstats-0.1.3.dist-info/RECORD
