Metadata-Version: 2.1
Name: orderstats
Version: 0.1.3
Summary: Research repository on outlier detection and analysis of heavy-tailed distributions.
Keywords: order statistics,outliers,outlier analysis,anomaly detection,pareto distribution,heavy-tailed distributions,visualization,simulation
Author: Ahmet Zahid Balcıoğlu, Oğuz Gürerk
Requires-Python: >=3.7
Classifier: Programming Language :: Python :: 3
Classifier: Programming Language :: Python :: 3 :: Only
Classifier: Intended Audience :: Developers
Classifier: Intended Audience :: Science/Research
Classifier: Topic :: Scientific/Engineering :: Visualization
Classifier: Topic :: Software Development :: Libraries :: Python Modules
Requires-Dist: dataclass_array
Requires-Dist: matplotlib
Requires-Dist: numpy
Requires-Dist: scipy
Requires-Dist: pytest>=3.4 ; extra == "dev"
Requires-Dist: pylint>=2.6.0 ; extra == "dev"
Requires-Dist: yapf ; extra == "dev"
Project-URL: homepage, https://github.com/Selozhd/orderstats
Project-URL: repository, https://github.com/Selozhd/orderstats
Provides-Extra: dev
